Metadata-Version: 2.1
Name: sqlx
Version: 0.1.1
Summary: SQL Extension | SQL 语法拓展，目标是打造 "易读易写 方便维护" 的 sql 脚本
Home-page: https://github.com/taojy123/sqlx
Author: tao.py
Author-email: taojy123@163.com
Maintainer: tao.py
Maintainer-email: taojy123@163.com
License: MIT License
Platform: all
Classifier: Programming Language :: Python
Classifier: Programming Language :: Python :: Implementation
Classifier: Programming Language :: Python :: 3 :: Only
Classifier: Topic :: Software Development :: Libraries
